base_client_library/__init__.py
base_client_library/exceptions.py
base_client_library/version.py
base_client_library/factories/__init__.py
base_client_library/factories/base.py
base_client_library-0.1b0.dist-info/METADATA
base_client_library-0.1b0.dist-info/WHEEL
base_client_library-0.1b0.dist-info/top_level.txt
base_client_library-0.1b0.dist-info/RECORD
